{
    "openapi": "3.0.0",
    "info": {
        "title": "CASMI APIs",
        "description": "CASMI: Cloud Agnostic Storage Management Interface",
        "version": "1.0"
    },
    "servers": [{ "url": "http://localhost:8000/api/v1" }],
    "paths": {
        "/files": {
            "get": {
                "summary": "Summary",
                "description": "Description",
                "tags": ["Files"],
                "security": [{ "Bearer token": [] }],
                "responses": {
                    "200": {
                        "description": "Success",
                        "content": {
                            "application/json": {
                                "schema": {
                                    "type": "object",
                                    "properties": {
                                        "success": { "type": "boolean" },
                                        "files": {
                                            "type": "array",
                                            "items": {
                                                "type": "object",
                                                "properties": {
                                                    "id": { "type": "integer" },
                                                    "name": { "type": "string" },
                                                    "size": { "type": "integer" },
                                                    "provider_key": { "type": "string" },
                                                    "folder_id": { "type": "integer" },
                                                    "store_id": { "type": "integer" },
                                                    "space_id": { "type": "integer" },
                                                    "space": { "type": "string" },
                                                    "provider_id": { "type": "integer" },
                                                    "provider": { "type": "string" }
                                                }
                                            }
                                        }
                                    }
                                }
                            }
                        }
                    },
                    "500": {
                        "description": "Server error.",
                        "content": {
                            "application/json": {
                                "schema": {
                                    "type": "object",
                                    "properties": {
                                        "success": { "type": "boolean" },
                                        "message": { "type": "string" }
                                    }
                                }
                            }
                        }
                    }
                }
            }
        },

        "/files/{id}": {
            "get": {
                "summary": "Summary",
                "description": "Description",
                "tags": ["Files"],
                "security": [{ "Bearer token": [] }],
                "parameters": [
                    {
                        "in": "path",
                        "name": "id",
                        "required": true,
                        "schema": {
                            "type": "string"
                        },
                        "description": "The file ID"
                    }
                ],
                "responses": {
                    "200": {
                        "description": "Success",
                        "content": {
                            "application/json": {
                                "schema": {
                                    "type": "object",
                                    "properties": {
                                        "success": { "type": "boolean" },
                                        "file": {
                                            "type": "object",
                                            "properties": {
                                                "id": { "type": "integer" },
                                                "name": { "type": "string" },
                                                "size": { "type": "integer" },
                                                "provider_key": { "type": "string" },
                                                "folder_id": { "type": "integer" },
                                                "store_id": { "type": "integer" },
                                                "space_id": { "type": "integer" },
                                                "space": { "type": "string" },
                                                "provider_id": { "type": "integer" },
                                                "provider": { "type": "string" }
                                            }
                                        }
                                    }
                                }
                            }
                        }
                    },
                    "400": {
                        "description": "Client error.",
                        "content": {
                            "application/json": {
                                "schema": {
                                    "type": "object",
                                    "properties": {
                                        "success": { "type": "boolean" },
                                        "message": { "type": "string" }
                                    }
                                }
                            }
                        }
                    },
                    "500": {
                        "description": "Server error.",
                        "content": {
                            "application/json": {
                                "schema": {
                                    "type": "object",
                                    "properties": {
                                        "success": { "type": "boolean" },
                                        "message": { "type": "string" }
                                    }
                                }
                            }
                        }
                    }
                }
            }
        },

        "/files/{id}/download": {
            "get": {
                "summary": "Summary",
                "description": "Description",
                "tags": ["Files"],
                "security": [{ "Bearer token": [] }],
                "parameters": [
                    {
                        "in": "path",
                        "name": "id",
                        "required": true,
                        "schema": {
                            "type": "string"
                        },
                        "description": "The file ID"
                    }
                ],
                "responses": {
                    "200": {
                        "description": "File",
                        "content": {
                            "application/json": {
                                "schema": {
                                    "type": "object",
                                    "properties": {
                                        "success": { "type": "boolean" },
                                        "download_link": { "type": "string" }
                                    }
                                }
                            }
                        }
                    }
                }
            }
        },

        "/files/upload": {
            "post": {
                "summary": "Summary",
                "description": "Description",
                "tags": ["Files"],
                "security": [{ "Bearer token": [] }],
                "requestBody": {
                    "required": true,
                    "content": {
                        "multipart/form-data": {
                            "schema": {
                                "type": "object",
                                "properties": {
                                    "file": { "type": "string", "format": "binary" },
                                    "store_id": { "type": "integer" },
                                    "destination": { "type": "string" }
                                }
                            }
                        }
                    }
                },
                "responses": {
                    "201": {
                        "description": "Created new file.",
                        "content": {
                            "application/json": {
                                "schema": {
                                    "type": "object",
                                    "properties": {
                                        "success": { "type": "boolean" },
                                        "file_id": { "type": "integer" }
                                    }
                                }
                            }
                        }
                    }
                }
            }
        },

        "/folders": {
            "get": {
                "summary": "Summary",
                "description": "Description",
                "tags": ["Folders"],
                "security": [{ "Bearer token": [] }],
                "responses": {
                    "200": {
                        "description": "Success",
                        "content": {
                            "application/json": {
                                "schema": {
                                    "type": "object",
                                    "properties": {
                                        "success": { "type": "boolean" },
                                        "folders": {
                                            "type": "array",
                                            "items": {
                                                "type": "object",
                                                "properties": {
                                                    "id": { "type": "integer" },
                                                    "provider_key": { "type": "string" },
                                                    "store_id": { "type": "integer" },
                                                    "space_id": { "type": "integer" },
                                                    "space": { "type": "string" },
                                                    "provider_id": { "type": "integer" },
                                                    "provider": { "type": "string" }
                                                }
                                            }
                                        }
                                    }
                                }
                            }
                        }
                    },
                    "500": {
                        "description": "Server error.",
                        "content": {
                            "application/json": {
                                "schema": {
                                    "type": "object",
                                    "properties": {
                                        "success": { "type": "boolean" },
                                        "message": { "type": "string" }
                                    }
                                }
                            }
                        }
                    }
                }
            }
        },

        "/folders/{id}": {
            "get": {
                "summary": "Summary",
                "description": "Description",
                "tags": ["Folders"],
                "security": [{ "Bearer token": [] }],
                "parameters": [
                    {
                        "in": "path",
                        "name": "id",
                        "required": true,
                        "schema": {
                            "type": "integer"
                        },
                        "description": "The folder ID"
                    }
                ],
                "responses": {
                    "200": {
                        "description": "Success",
                        "content": {
                            "application/json": {
                                "schema": {
                                    "type": "object",
                                    "properties": {
                                        "success": { "type": "boolean" },
                                        "folder": {
                                            "type": "object",
                                            "properties": {
                                                "id": { "type": "integer" },
                                                "provider_key": { "type": "string" },
                                                "store_id": { "type": "integer" },
                                                "space_id": { "type": "integer" },
                                                "space": { "type": "string" },
                                                "provider_id": { "type": "integer" },
                                                "provider": { "type": "string" }
                                            }
                                        }
                                    }
                                }
                            }
                        }
                    },
                    "400": {
                        "description": "Client error.",
                        "content": {
                            "application/json": {
                                "schema": {
                                    "type": "object",
                                    "properties": {
                                        "success": { "type": "boolean" },
                                        "message": { "type": "string" }
                                    }
                                }
                            }
                        }
                    },
                    "500": {
                        "description": "Server error.",
                        "content": {
                            "application/json": {
                                "schema": {
                                    "type": "object",
                                    "properties": {
                                        "success": { "type": "boolean" },
                                        "message": { "type": "string" }
                                    }
                                }
                            }
                        }
                    }
                }
            }
        },

        "/providers": {
            "get": {
                "summary": "Summary",
                "description": "Description",
                "tags": ["Providers"],
                "security": [{ "Bearer token": [] }],
                "responses": {
                    "200": {
                        "description": "Success",
                        "content": {
                            "application/json": {
                                "schema": {
                                    "type": "object",
                                    "properties": {
                                        "success": { "type": "boolean" },
                                        "providers": {
                                            "type": "array",
                                            "items": {
                                                "type": "object",
                                                "properties": {
                                                    "id": { "type": "integer" },
                                                    "code": { "type": "string" },
                                                    "public_name": { "type": "string" }
                                                }
                                            }
                                        }
                                    }
                                }
                            }
                        }
                    },
                    "500": {
                        "description": "Server error.",
                        "content": {
                            "application/json": {
                                "schema": {
                                    "type": "object",
                                    "properties": {
                                        "success": { "type": "boolean" },
                                        "message": { "type": "string" }
                                    }
                                }
                            }
                        }
                    }
                }
            },
            "post": {
                "summary": "Summary",
                "description": "Description",
                "tags": ["Providers"],
                "security": [{ "Bearer token": [] }],
                "requestBody": {
                    "required": true,
                    "content": {
                        "application/json": {
                            "schema": {
                                "type": "object",
                                "properties": {
                                    "code": { "type": "string" },
                                    "public_name": { "type": "string" }
                                }
                            }
                        }
                    }
                },
                "responses": {
                    "201": {
                        "description": "Created new provider.",
                        "content": {
                            "application/json": {
                                "schema": {
                                    "type": "object",
                                    "properties": {
                                        "success": { "type": "boolean" },
                                        "provider_id": { "type": "integer" }
                                    }
                                }
                            }
                        }
                    },
                    "400": {
                        "description": "Client error.",
                        "content": {
                            "application/json": {
                                "schema": {
                                    "type": "object",
                                    "properties": {
                                        "success": { "type": "boolean" },
                                        "message": { "type": "string" }
                                    }
                                }
                            }
                        }
                    },
                    "500": {
                        "description": "Server error.",
                        "content": {
                            "application/json": {
                                "schema": {
                                    "type": "object",
                                    "properties": {
                                        "success": { "type": "boolean" },
                                        "message": { "type": "string" }
                                    }
                                }
                            }
                        }
                    }
                }
            }
        },

        "/providers/{id}": {
            "get": {
                "summary": "Summary",
                "description": "Description",
                "tags": ["Providers"],
                "security": [{ "Bearer token": [] }],
                "parameters": [
                    {
                        "in": "path",
                        "name": "id",
                        "required": true,
                        "schema": {
                            "type": "integer"
                        },
                        "description": "The provider ID"
                    }
                ],
                "responses": {
                    "200": {
                        "description": "Success",
                        "content": {
                            "application/json": {
                                "schema": {
                                    "type": "object",
                                    "properties": {
                                        "success": { "type": "boolean" },
                                        "provider": {
                                            "type": "object",
                                            "properties": {
                                                "id": { "type": "integer" },
                                                "code": { "type": "string" },
                                                "public_name": { "type": "string" }
                                            }
                                        }
                                    }
                                }
                            }
                        }
                    },
                    "400": {
                        "description": "Client error.",
                        "content": {
                            "application/json": {
                                "schema": {
                                    "type": "object",
                                    "properties": {
                                        "success": { "type": "boolean" },
                                        "message": { "type": "string" }
                                    }
                                }
                            }
                        }
                    },
                    "500": {
                        "description": "Server error.",
                        "content": {
                            "application/json": {
                                "schema": {
                                    "type": "object",
                                    "properties": {
                                        "success": { "type": "boolean" },
                                        "message": { "type": "string" }
                                    }
                                }
                            }
                        }
                    }
                }
            }
        },

        "/spaces": {
            "get": {
                "summary": "Summary",
                "description": "Description",
                "tags": ["Spaces"],
                "security": [{ "Bearer token": [] }],
                "responses": {
                    "200": {
                        "description": "Success",
                        "content": {
                            "application/json": {
                                "schema": {
                                    "type": "object",
                                    "properties": {
                                        "success": { "type": "boolean" },
                                        "spaces": {
                                            "type": "array",
                                            "items": {
                                                "type": "object",
                                                "properties": {
                                                    "id": { "type": "integer" },
                                                    "name": { "type": "string" },
                                                    "providers": {
                                                        "type": "array",
                                                        "items": { "type": "strin" }
                                                    }
                                                }
                                            }
                                        }
                                    }
                                }
                            }
                        }
                    },
                    "500": {
                        "description": "Server error.",
                        "content": {
                            "application/json": {
                                "schema": {
                                    "type": "object",
                                    "properties": {
                                        "success": { "type": "boolean" },
                                        "message": { "type": "string" }
                                    }
                                }
                            }
                        }
                    }
                }
            },
            "post": {
                "summary": "Summary",
                "description": "Description",
                "tags": ["Spaces"],
                "security": [{ "Bearer token": [] }],
                "requestBody": {
                    "required": true,
                    "content": {
                        "application/json": {
                            "schema": {
                                "type": "object",
                                "properties": {
                                    "name": { "type": "string" },
                                    "provider_ids": {
                                        "type": "array",
                                        "items": {
                                            "type": "integer"
                                        },
                                        "minItems": 1
                                    },
                                    "default_secrets": { "type": "boolean" },
                                    "secrets": { "type": "object" }
                                }
                            }
                        }
                    }
                },
                "responses": {
                    "201": {
                        "description": "Created new space.",
                        "content": {
                            "application/json": {
                                "schema": {
                                    "type": "object",
                                    "properties": {
                                        "success": { "type": "boolean" },
                                        "space_id": { "type": "integer" }
                                    }
                                }
                            }
                        }
                    },
                    "400": {
                        "description": "Client error.",
                        "content": {
                            "application/json": {
                                "schema": {
                                    "type": "object",
                                    "properties": {
                                        "success": { "type": "boolean" },
                                        "message": { "type": "string" }
                                    }
                                }
                            }
                        }
                    },
                    "500": {
                        "description": "Server error.",
                        "content": {
                            "application/json": {
                                "schema": {
                                    "type": "object",
                                    "properties": {
                                        "success": { "type": "boolean" },
                                        "message": { "type": "string" }
                                    }
                                }
                            }
                        }
                    }
                }
            }
        },

        "/spaces/{id}": {
            "get": {
                "summary": "Summary",
                "description": "Description",
                "tags": ["Spaces"],
                "security": [{ "Bearer token": [] }],
                "parameters": [
                    {
                        "in": "path",
                        "name": "id",
                        "required": true,
                        "schema": {
                            "type": "integer"
                        },
                        "description": "The space ID"
                    }
                ],
                "responses": {
                    "200": {
                        "description": "Success",
                        "content": {
                            "application/json": {
                                "schema": {
                                    "type": "object",
                                    "properties": {
                                        "success": { "type": "boolean" },
                                        "space": {
                                            "type": "object",
                                            "properties": {
                                                "id": { "type": "integer" },
                                                "name": { "type": "string" },
                                                "providers": {
                                                    "type": "array",
                                                    "items": { "type": "strin" }
                                                }
                                            }
                                        }
                                    }
                                }
                            }
                        }
                    },
                    "400": {
                        "description": "Client error.",
                        "content": {
                            "application/json": {
                                "schema": {
                                    "type": "object",
                                    "properties": {
                                        "success": { "type": "boolean" },
                                        "message": { "type": "string" }
                                    }
                                }
                            }
                        }
                    },
                    "500": {
                        "description": "Server error.",
                        "content": {
                            "application/json": {
                                "schema": {
                                    "type": "object",
                                    "properties": {
                                        "success": { "type": "boolean" },
                                        "message": { "type": "string" }
                                    }
                                }
                            }
                        }
                    }
                }
            }
        },

        "/stores": {
            "get": {
                "summary": "Summary",
                "description": "Description",
                "tags": ["Stores"],
                "security": [{ "Bearer token": [] }],
                "responses": {
                    "200": {
                        "description": "Success",
                        "content": {
                            "application/json": {
                                "schema": {
                                    "type": "object",
                                    "properties": {
                                        "success": { "type": "boolean" },
                                        "stores": {
                                            "type": "array",
                                            "items": {
                                                "type": "object",
                                                "properties": {
                                                    "id": { "type": "integer" },
                                                    "file_count": { "type": "integer" },
                                                    "space_id": { "type": "integer" },
                                                    "space": { "type": "string" },
                                                    "provider_id": { "type": "integer" },
                                                    "provider": { "type": "string" }
                                                }
                                            }
                                        }
                                    }
                                }
                            }
                        }
                    },
                    "500": {
                        "description": "Server error.",
                        "content": {
                            "application/json": {
                                "schema": {
                                    "type": "object",
                                    "properties": {
                                        "success": { "type": "boolean" },
                                        "message": { "type": "string" }
                                    }
                                }
                            }
                        }
                    }
                }
            }
        },

        "/stores/{id}": {
            "get": {
                "summary": "Summary",
                "description": "Description",
                "tags": ["Stores"],
                "security": [{ "Bearer token": [] }],
                "parameters": [
                    {
                        "in": "path",
                        "name": "id",
                        "required": true,
                        "schema": {
                            "type": "string"
                        },
                        "description": "The store ID"
                    }
                ],
                "responses": {
                    "200": {
                        "description": "Success",
                        "content": {
                            "application/json": {
                                "schema": {
                                    "type": "object",
                                    "properties": {
                                        "success": { "type": "boolean" },
                                        "store": {
                                            "type": "object",
                                            "properties": {
                                                "id": { "type": "integer" },
                                                "file_count": { "type": "integer" },
                                                "space_id": { "type": "integer" },
                                                "space": { "type": "string" },
                                                "provider_id": { "type": "integer" },
                                                "provider": { "type": "string" }
                                            }
                                        }
                                    }
                                }
                            }
                        }
                    },
                    "400": {
                        "description": "Client error.",
                        "content": {
                            "application/json": {
                                "schema": {
                                    "type": "object",
                                    "properties": {
                                        "success": { "type": "boolean" },
                                        "message": { "type": "string" }
                                    }
                                }
                            }
                        }
                    },
                    "500": {
                        "description": "Server error.",
                        "content": {
                            "application/json": {
                                "schema": {
                                    "type": "object",
                                    "properties": {
                                        "success": { "type": "boolean" },
                                        "message": { "type": "string" }
                                    }
                                }
                            }
                        }
                    }
                }
            }
        },

        "/users/": {
            "post": {
                "summary": "Summary",
                "description": "Description",
                "tags": ["Users"],
                "security": [{ "Bearer token": [] }],
                "requestBody": {
                    "required": true,
                    "content": {
                        "application/json": {
                            "schema": {
                                "type": "object",
                                "properties": {
                                    "username": { "type": "string" },
                                    "password": { "type": "string" },
                                    "name": { "type": "string" },
                                    "user_type": { "type": "string" }
                                }
                            }
                        }
                    }
                },
                "responses": {
                    "200": {
                        "description": "Success",
                        "content": {
                            "application/json": {
                                "schema": {
                                    "type": "object",
                                    "properties": {
                                        "success": { "type": "boolean" },
                                        "store": {
                                            "type": "object",
                                            "properties": {
                                                "uid": { "type": "integer" },
                                                "name": { "type": "string" },
                                                "username": { "type": "string" }
                                            }
                                        }
                                    }
                                }
                            }
                        }
                    },
                    "400": {
                        "description": "Client error.",
                        "content": {
                            "application/json": {
                                "schema": {
                                    "type": "object",
                                    "properties": {
                                        "success": { "type": "boolean" },
                                        "message": { "type": "string" }
                                    }
                                }
                            }
                        }
                    },
                    "500": {
                        "description": "Server error.",
                        "content": {
                            "application/json": {
                                "schema": {
                                    "type": "object",
                                    "properties": {
                                        "success": { "type": "boolean" },
                                        "message": { "type": "string" }
                                    }
                                }
                            }
                        }
                    }
                }
            }
        },

        "/users/login": {
            "post": {
                "summary": "Summary",
                "description": "Description",
                "tags": ["Users"],
                "requestBody": {
                    "required": true,
                    "content": {
                        "application/json": {
                            "schema": {
                                "type": "object",
                                "properties": {
                                    "username": { "type": "string" },
                                    "password": { "type": "string" }
                                }
                            }
                        }
                    }
                },
                "responses": {
                    "200": {
                        "description": "Success",
                        "content": {
                            "application/json": {
                                "schema": {
                                    "type": "object",
                                    "properties": {
                                        "success": { "type": "boolean" },
                                        "store": {
                                            "type": "object",
                                            "properties": {
                                                "uid": { "type": "integer" },
                                                "name": { "type": "string" },
                                                "username": { "type": "string" },
                                                "id_token": { "type": "string" }
                                            }
                                        }
                                    }
                                }
                            }
                        }
                    },
                    "400": {
                        "description": "Client error.",
                        "content": {
                            "application/json": {
                                "schema": {
                                    "type": "object",
                                    "properties": {
                                        "success": { "type": "boolean" },
                                        "message": { "type": "string" }
                                    }
                                }
                            }
                        }
                    },
                    "500": {
                        "description": "Server error.",
                        "content": {
                            "application/json": {
                                "schema": {
                                    "type": "object",
                                    "properties": {
                                        "success": { "type": "boolean" },
                                        "message": { "type": "string" }
                                    }
                                }
                            }
                        }
                    }
                }
            }
        }
    },
    "components": {
        "securitySchemes": {
            "Bearer token": {
                "type": "http",
                "scheme": "bearer",
                "bearerFormat": "JWT"
            }
        }
    }
}
